{
    "meta": {
        "title": "Complete Theme Customization Guide",
        "theme": "default",
        "themeConfig": {
            "colors": {
                "primary": "#a855f7",
                "secondary": "#c084fc",
                "accent": "#e879f9",
                "background": "#0c0a1d",
                "surface": "#1a1625",
                "text": "#f3e8ff",
                "textSecondary": "#e9d5ff",
                "muted": "#a78bfa",
                "success": "#22c55e",
                "warning": "#eab308",
                "danger": "#ef4444",
                "info": "#a855f7",
                "border": "rgba(168, 85, 247, 0.2)",
                "borderSubtle": "rgba(168, 85, 247, 0.1)",
                "gradientFrom": "#a855f7",
                "gradientVia": "#8b5cf6",
                "gradientTo": "#6366f1"
            },
            "typography": {
                "fontFamily": {
                    "heading": "Outfit, Inter, sans-serif",
                    "body": "Inter, system-ui, sans-serif",
                    "mono": "JetBrains Mono, monospace"
                }
            },
            "effects": {
                "useGradients": true,
                "gradientDirection": "to-br",
                "useGlass": true,
                "glassOpacity": 0.04,
                "glassBlur": "24px",
                "glassBorderOpacity": 0.08,
                "useOrb": true,
                "orbOpacity": 0.5,
                "orbBlur": "140px",
                "orbSize": "70vw",
                "useShadows": true,
                "shadowIntensity": "lg",
                "shadowColor": "rgba(168, 85, 247, 0.3)",
                "animationsEnabled": true,
                "transitionDuration": "0.3s",
                "transitionEasing": "cubic-bezier(0.16, 1, 0.3, 1)",
                "hoverScale": 1.05
            },
            "components": {
                "cardRadius": "1.5rem",
                "cardPadding": "2rem",
                "cardBorderWidth": "1px",
                "buttonRadius": "9999px",
                "buttonPadding": "0.75rem 1.5rem",
                "buttonFontWeight": 700,
                "timelineNodeSize": "1rem",
                "timelineLineWidth": "2px",
                "timelineNodeColor": "#a855f7",
                "timelineLineColor": "rgba(168, 85, 247, 0.3)",
                "tagPadding": "0.25rem 1rem",
                "tagRadius": "9999px",
                "tagFontSize": "0.75rem"
            }
        }
    },
    "slides": [
        {
            "type": "statement",
            "tag": "Theming System v9",
            "title": "80+ Customizable CSS Variables",
            "subtitle": "Full control over colors, typography, effects, and component styling",
            "notes": "# ThemeConfig Overview\n\nThe new theming system provides 80+ CSS custom properties organized in categories:\n\n## Categories\n- **colors**: 25+ color tokens (primary, secondary, accent, background, surface, text, semantic states, gradients)\n- **typography**: Font families (heading, body, mono), sizes (xs-7xl), weights (light-extrabold), line heights, letter spacing\n- **spacing**: 9 tokens (none, xs, sm, md, lg, xl, 2xl, 3xl, 4xl)\n- **borderRadius**: 8 tokens (none, sm, md, lg, xl, 2xl, 3xl, full)\n- **effects**: Gradients, shadows, glass, orb, animations\n- **components**: Button, card, timeline, tag, progress bar specific tokens\n\n## Usage\nSet in meta.themeConfig with any subset of options."
        },
        {
            "type": "features",
            "title": "Color System",
            "description": "25+ semantic color tokens for complete brand control",
            "features": [
                {
                    "title": "Core Colors",
                    "desc": "primary, secondary, accent, background, surface, text, textSecondary, muted",
                    "icon": "palette"
                },
                {
                    "title": "Semantic States",
                    "desc": "success (#22c55e), warning (#eab308), danger (#ef4444), info (uses primary)",
                    "icon": "info-circle"
                },
                {
                    "title": "UI Colors",
                    "desc": "border, borderSubtle, shadow, overlay, highlight for interface elements",
                    "icon": "layer-group"
                },
                {
                    "title": "Interactive",
                    "desc": "buttonPrimary, buttonPrimaryText, buttonSecondary, link, linkHover",
                    "icon": "hand-pointer"
                },
                {
                    "title": "Gradients",
                    "desc": "gradientFrom, gradientVia, gradientTo for multi-stop gradients",
                    "icon": "swatchbook"
                },
                {
                    "title": "RGB Support",
                    "desc": "All colors auto-generate RGB triplets for alpha usage in rgba()",
                    "icon": "fill-drip"
                }
            ],
            "notes": "# Color Tokens Reference\n\n## Core Colors\n- `primary`: Main brand color, used for accents and CTAs\n- `secondary`: Complementary brand color\n- `accent`: Tertiary highlight color\n- `background`: Main slide background (#0c0a1d in this theme)\n- `surface`: Cards, panels, elevated surfaces (#1a1625)\n- `text`: Primary text color (#f3e8ff)\n- `textSecondary`: Secondary body text\n- `muted`: Subdued text, captions\n\n## State Colors\n- `success`: Positive actions, confirmations\n- `warning`: Caution states\n- `danger`: Errors, destructive actions\n- `info`: Informational highlights\n\n## Gradient Colors\n- `gradientFrom`: Starting color\n- `gradientVia`: Middle color (optional)\n- `gradientTo`: Ending color\n\nAll hex colors automatically generate --lumina-color-{name}-rgb CSS variables."
        },
        {
            "type": "timeline",
            "title": "Effects Configuration",
            "subtitle": "Visual enhancements for premium feel",
            "timeline": [
                {
                    "date": "Gradients",
                    "title": "useGradients: true",
                    "description": "gradientDirection: 'to-br' | 'to-t' | 'to-b' | 'to-l' | 'to-r' | 'to-tl' | 'to-tr' | 'to-bl'"
                },
                {
                    "date": "Shadows",
                    "title": "useShadows: true",
                    "description": "shadowIntensity: 'none' | 'sm' | 'md' | 'lg' | 'xl' | '2xl', shadowColor: 'rgba(...)'"
                },
                {
                    "date": "Glass",
                    "title": "useGlass: true",
                    "description": "glassOpacity: 0.04, glassBlur: '24px', glassBorderOpacity: 0.08"
                },
                {
                    "date": "Orb",
                    "title": "useOrb: true",
                    "description": "orbOpacity: 0.5, orbBlur: '140px', orbSize: '70vw'"
                },
                {
                    "date": "Animations",
                    "title": "animationsEnabled: true",
                    "description": "transitionDuration: '0.3s', transitionEasing: 'cubic-bezier(...)', hoverScale: 1.05"
                }
            ],
            "notes": "# Effects Configuration\n\n## Gradients\n- `useGradients`: boolean - Master toggle\n- `gradientDirection`: Direction enum\n  - 'to-t' (top), 'to-b' (bottom), 'to-l' (left), 'to-r' (right)\n  - 'to-tl', 'to-tr', 'to-bl', 'to-br' (diagonals)\n\n## Shadows\n- `useShadows`: boolean\n- `shadowIntensity`: 'none' | 'sm' | 'md' | 'lg' | 'xl' | '2xl'\n- `shadowColor`: Any CSS color string\n\n## Glassmorphism\n- `useGlass`: boolean - Frosted glass panels\n- `glassOpacity`: 0-1 (default 0.03)\n- `glassBlur`: CSS blur value (default '20px')\n- `glassBorderOpacity`: 0-1 for subtle borders\n\n## Ambient Orb\n- `useOrb`: boolean - Background glow effect\n- `orbOpacity`: 0-1 (default 0.4)\n- `orbBlur`: CSS blur (default '120px')\n- `orbSize`: CSS size (default '60vw')\n\n## Animations\n- `animationsEnabled`: Master toggle\n- `transitionDuration`: Default '0.3s'\n- `transitionEasing`: CSS easing function\n- `hoverScale`: Scale on hover (default 1.05)"
        },
        {
            "type": "steps",
            "title": "Component Tokens",
            "subtitle": "Fine-tune individual UI components",
            "steps": [
                {
                    "step": "01",
                    "title": "Button Styling",
                    "description": "buttonRadius, buttonPadding, buttonFontWeight, buttonTextTransform",
                    "icon": "rectangle-ad"
                },
                {
                    "step": "02",
                    "title": "Card Styling",
                    "description": "cardRadius, cardPadding, cardBorderWidth, cardBackground",
                    "icon": "square"
                },
                {
                    "step": "03",
                    "title": "Timeline Styling",
                    "description": "timelineNodeSize, timelineLineWidth, timelineNodeColor, timelineLineColor",
                    "icon": "timeline"
                },
                {
                    "step": "04",
                    "title": "Tag/Badge Styling",
                    "description": "tagPadding, tagRadius, tagFontSize",
                    "icon": "tag"
                },
                {
                    "step": "05",
                    "title": "Progress Bars",
                    "description": "progressHeight, progressRadius, progressBackground, progressFill",
                    "icon": "bars-progress"
                }
            ],
            "notes": "# Component-Specific Tokens\n\n## Buttons\n- `buttonRadius`: Border radius (default '9999px' = pill)\n- `buttonPadding`: CSS padding (default '0.75rem 1.5rem')\n- `buttonFontWeight`: Number 100-900 (default 700)\n- `buttonTextTransform`: 'none' | 'uppercase' | 'capitalize'\n\n## Cards\n- `cardRadius`: Border radius (default '1.5rem')\n- `cardPadding`: CSS padding (default '2rem')\n- `cardBorderWidth`: Border thickness (default '1px')\n- `cardBackground`: Override background color\n\n## Timeline\n- `timelineNodeSize`: Node diameter (default '1rem')\n- `timelineLineWidth`: Connecting line width (default '2px')\n- `timelineNodeColor`: Node color (defaults to primary)\n- `timelineLineColor`: Line color (defaults to border)\n\n## Tags/Badges\n- `tagPadding`: CSS padding (default '0.25rem 1rem')\n- `tagRadius`: Border radius (default '9999px')\n- `tagFontSize`: Font size (default '0.75rem')\n\n## Progress Bars\n- `progressHeight`: Height (default '0.5rem')\n- `progressRadius`: Border radius (default '9999px')\n- `progressBackground`: Track color\n- `progressFill`: Fill color"
        },
        {
            "type": "flex",
            "direction": "horizontal",
            "gap": "lg",
            "elements": [
                {
                    "type": "content",
                    "size": "half",
                    "valign": "center",
                    "halign": "left",
                    "gap": "md",
                    "padding": "xl",
                    "elements": [
                        {
                            "type": "title",
                            "text": "Typography System",
                            "size": "2xl"
                        },
                        {
                            "type": "text",
                            "text": "11 font sizes from xs (0.75rem) to 7xl (4.5rem)",
                            "muted": true
                        },
                        {
                            "type": "spacer",
                            "size": "sm"
                        },
                        {
                            "type": "bullets",
                            "items": [
                                "fontFamily: heading, body, mono",
                                "fontSize: xs, sm, base, lg, xl, 2xl-7xl",
                                "fontWeight: light (300) to extrabold (800)",
                                "lineHeight: tight (1.1) to loose (2)",
                                "letterSpacing: tighter to widest"
                            ]
                        }
                    ]
                },
                {
                    "type": "content",
                    "size": "half",
                    "valign": "center",
                    "halign": "left",
                    "gap": "md",
                    "padding": "xl",
                    "elements": [
                        {
                            "type": "title",
                            "text": "Spacing & Radius",
                            "size": "2xl"
                        },
                        {
                            "type": "text",
                            "text": "Consistent design tokens across all components",
                            "muted": true
                        },
                        {
                            "type": "spacer",
                            "size": "sm"
                        },
                        {
                            "type": "stepper",
                            "items": [
                                {
                                    "step": "S",
                                    "title": "Spacing",
                                    "description": "none, xs, sm, md, lg, xl, 2xl, 3xl, 4xl"
                                },
                                {
                                    "step": "R",
                                    "title": "Border Radius",
                                    "description": "none, sm, md, lg, xl, 2xl, 3xl, full"
                                }
                            ]
                        }
                    ]
                }
            ],
            "notes": "# Typography Tokens\n\n## Font Families\n- `typography.fontFamily.heading`: Headings (default 'Inter, sans-serif')\n- `typography.fontFamily.body`: Body text (default 'Inter, sans-serif')\n- `typography.fontFamily.mono`: Code (default 'monospace')\n\n## Font Sizes (CSS Variables: --lumina-text-*)\n- xs: 0.75rem | sm: 0.875rem | base: 1rem\n- lg: 1.125rem | xl: 1.25rem | 2xl: 1.5rem\n- 3xl: 1.875rem | 4xl: 2.25rem | 5xl: 3rem\n- 6xl: 3.75rem | 7xl: 4.5rem\n\n## Font Weights (CSS Variables: --lumina-font-weight-*)\n- light: 300 | normal: 400 | medium: 500\n- semibold: 600 | bold: 700 | extrabold: 800\n\n## Line Heights (CSS Variables: --lumina-leading-*)\n- tight: 1.1 | snug: 1.25 | normal: 1.5\n- relaxed: 1.625 | loose: 2\n\n## Letter Spacing (CSS Variables: --lumina-tracking-*)\n- tighter: -0.05em | tight: -0.025em | normal: 0\n- wide: 0.025em | wider: 0.05em | widest: 0.1em\n\n# Spacing Tokens (CSS Variables: --lumina-space-*)\nnone: 0 | xs: 0.25rem | sm: 0.5rem | md: 1rem\nlg: 1.5rem | xl: 2rem | 2xl: 3rem | 3xl: 4rem | 4xl: 6rem\n\n# Border Radius (CSS Variables: --lumina-radius-*)\nnone: 0 | sm: 0.25rem | md: 0.5rem | lg: 0.75rem\nxl: 1rem | 2xl: 1.5rem | 3xl: 2rem | full: 9999px"
        },
        {
            "type": "statement",
            "tag": "Quick Start",
            "title": "Start with a Preset, Override What You Need",
            "subtitle": "Use theme: 'preset' + themeConfig for partial overrides. Lumina deep-merges your changes.",
            "notes": "# Quick Reference\n\n## Preset Names\n- `default`: Blue on dark\n- `ocean`: Cyan on slate\n- `midnight`: Indigo on black\n- `forest`: Emerald on dark green\n- `cyber`: Pink on zinc\n- `latte`: Amber on cream (light mode)\n- `sunset`: Orange-rose gradient\n- `monochrome`: Black and white\n\n## Minimal Override Example\n```json\n{\n  \"meta\": {\n    \"theme\": \"midnight\",\n    \"themeConfig\": {\n      \"colors\": { \"primary\": \"#ff6b6b\" }\n    }\n  }\n}\n```\n\n## Full Custom Example\nSee this deck's meta.themeConfig for all available options.\n\n## CSS Variables\nAll tokens are exposed as --lumina-* CSS custom properties for external styling."
        }
    ]
}